llm_azure_api_embed.py
llm_azure_api_embed-0.1.dist-info/LICENSE
llm_azure_api_embed-0.1.dist-info/METADATA
llm_azure_api_embed-0.1.dist-info/WHEEL
llm_azure_api_embed-0.1.dist-info/entry_points.txt
llm_azure_api_embed-0.1.dist-info/top_level.txt
llm_azure_api_embed-0.1.dist-info/RECORD
