Metadata-Version: 2.1
Name: llm-azure-api-embed
Version: 0.1
Summary: Create embeddings using the Azure API
Author: Ronald Luitwieler
License: Apache-2.0
Project-URL: Homepage, https://github.com/orangewise/llm-azure-api-embed
Project-URL: Changelog, https://github.com/orangewise/llm-azure-api-embed/releases
Project-URL: Issues, https://github.com/orangewise/llm-azure-api-embed/issues
Classifier: License :: OSI Approved :: Apache Software License
License-File: LICENSE
Requires-Dist: llm
